.gitignore
.gitmodules
HISTORY.rst
LICENCE
MANIFEST.in
Makefile
README.rst
distribute_setup.py
setup.py
docs/Makefile
docs/api.rst
docs/conf.py
docs/history.rst
docs/index.rst
docs/make.bat
docs/overview.rst
skeleton/__init__.py
skeleton/core.py
skeleton/utils.py
skeleton/examples/__init__.py
skeleton/examples/basicpackage.py
skeleton/examples/licenses.py
skeleton/examples/mkmodule.py
skeleton/examples/sphinxpackage.py
skeleton/examples/basic-module/README.rst
skeleton/examples/basic-module/setup.py_tmpl
skeleton/examples/basic-module/{module_name}.py
skeleton/examples/basic-package/MANIFEST.in
skeleton/examples/basic-package/README.rst
skeleton/examples/basic-package/distribute_setup.py
skeleton/examples/basic-package/setup.py_tmpl
skeleton/examples/licenses/bsd/LICENSE_tmpl
skeleton/examples/licenses/gpl/COPYING
skeleton/examples/licenses/gpl/LICENSE_tmpl
skeleton/examples/licenses/lgpl/COPYING
skeleton/examples/licenses/lgpl/COPYING.LESSER
skeleton/examples/licenses/lgpl/LICENSE_tmpl
skeleton/examples/licenses/no-license/LICENSE_tmpl
skeleton/examples/sphinx-package/HISTORY
skeleton/examples/sphinx-package/INSTALL_tmpl
skeleton/examples/sphinx-package/MANIFEST.in
skeleton/examples/sphinx-package/README_tmpl
skeleton/examples/sphinx-package/VERSION
skeleton/examples/sphinx-package/setup.cfg
skeleton/examples/sphinx-package/setup.py_tmpl
skeleton/examples/sphinx-package/docs/Makefile_tmpl
skeleton/examples/sphinx-package/docs/make.bat_tmpl
skeleton/examples/sphinx-package/docs/build/empty_file
skeleton/examples/sphinx-package/docs/source/conf.py_tmpl
skeleton/examples/sphinx-package/docs/source/history.rst
skeleton/examples/sphinx-package/docs/source/index.rst_tmpl
skeleton/examples/sphinx-package/docs/source/installation.rst
skeleton/examples/sphinx-package/docs/source/overview.rst
skeleton/tests/__init__.py
skeleton/tests/test_core.py
skeleton/tests/test_examples.py
skeleton/tests/test_utils.py
skeleton/tests/utils.py
skeleton_stu.egg-info/PKG-INFO
skeleton_stu.egg-info/SOURCES.txt
skeleton_stu.egg-info/dependency_links.txt
skeleton_stu.egg-info/entry_points.txt
skeleton_stu.egg-info/not-zip-safe
skeleton_stu.egg-info/requires.txt
skeleton_stu.egg-info/top_level.txt